{
  "project_info": {
    "project_number": "563579471585",
    "firebase_url": "https://b2bprojectdata.firebaseio.com",
    "project_id": "b2bprojectdata",
    "storage_bucket": "b2bprojectdata.appspot.com"
  },
  "client": [
    {
      "client_info": {
        "mobilesdk_app_id": "1:563579471585:android:48e5e022e646bda8ff99a0",
        "android_client_info": {
          "package_name": "b2bexportimport.b2b_trade"
        }
      },
      "oauth_client": [
        {
          "client_id": "563579471585-7m320h9a4l87ans5g1jsen097slk6kro.apps.googleusercontent.com",
          "client_type": 3
        }
      ],
      "api_key": [
        {
          "current_key": "AIzaSyAUKnaFc-RRYvtpAFgjiVGBt-ar-RZuGGw"
        }
      ],
      "services": {
        "appinvite_service": {
          "other_platform_oauth_client": [
            {
              "client_id": "563579471585-7m320h9a4l87ans5g1jsen097slk6kro.apps.googleusercontent.com",
              "client_type": 3
            }
          ]
        }
      }
    }
  ],
  "configuration_version": "1"
}